package com.wzh.thik.in.java.thirteen;/**
 * Created by Administrator on 2017/11/21.
 */

/**
 * @author:Administrator
 * @date:2017/11/21
 * @description:
 */

public class ExOne {
//    0:
//            3:
//            4:	new dup
//    invokespecial	#5;
//
//    #6;	//class StringBuilder
//
////StringBuilder."<init>":()
//    7:	ldc	#7;
//    9:	invokevirtual	#8;	//StringBuilder.append:()
//    12:	aload_0
//    13:	getfield	#9;
//    16:	invokevirtual	#8;	//StringBuilder.append:()
//    19:	ldc	#10;
//    21:	invokevirtual	#8;	//StringBuilder.append:()
//    24:	ldc	#11;
//    26:	invokevirtual	#8;	//StringBuilder.append:()
//    29:	aload_0
//    30:	getfield	#12;
//    33:	invokevirtual	#8;	//StringBuilder.append:()
//    36:	ldc	#10;
//    38:	invokevirtual	#8;	//StringBuilder.append:()
//    41:	ldc	#13;
//    43:	invokevirtual	#8;	//StringBuilder.append:()
//    46:	aload_0
//    47:	getfield	#14;
//    50:	invokevirtual	#8;	//StringBuilder.append:()
//    53:	ldc	#10;
//    55:	invokevirtual	#8;	//StringBuilder.append:()
//    58:	ldc	#15;
//    60:	invokevirtual	#8;	//StringBuilder.append:()
//    63:	aload_0
//    64:	getfield	#16;
//    67:	invokevirtual	#8;	//StringBuilder.append:()
//    70:	ldc	#17;
//    72:	invokevirtual	#8;	//StringBuilder.append:()
//    75:	ldc	#18;
//    77:	invokevirtual	#8;	//StringBuilder.append:()
//    80:	aload_0
//    81:	getfield	#19;
//
//
//    84:	invokevirtual	#20;	//StringBuilder.append:()
//    87:	ldc	#10;
//    89:	invokevirtual	#8;	//StringBuilder.append:()
//    92:	ldc	#21;
//    94:	invokevirtual	#8;	//StringBuilder.append:()
//    97:	aload_0
//    98:	getfield	#22;
//    101:	invokevirtual	#23;	//StringBuilder.append:()
//    104:	ldc	#10;
//    106:	invokevirtual	#8;	//StringBuilder.append:()
//    109:	ldc	#24;
//    111:	invokevirtual	#8;	//StringBuilder.append:()
//    114:	aload_0
//    115:	getfield	#4;
//    118:	invokevirtual	#25;	//StringBuilder.append:()
//    121:	invokevirtual	#26;	//StringBuilder.toString:()
//    124:	areturn
//}
}
